{
  "pass": true,
  "todo_id": "wsg-w5-perf-budgets",
  "agent_run": "world_studio_builder-68539695",
  "iteration": "plan-complete-ci-green",
  "wps_touched": ["W0", "W1", "W2", "W3", "W4", "W5", "WP-UX-13", "PH-UX"],
  "smokes_run": [
    "scripts/world-studio-gui-plan-gates.sh",
    "scripts/world-studio-gui-plan-completion-gate.sh"
  ],
  "native_only": true,
  "styled_chrome_minimum": true,
  "phase0_styled_chrome": true,
  "phases_w0_w5": "done",
  "gates": {
    "world_studio_gui_plan_gates": "pass",
    "world_studio_gui_plan_completion_gate": "pass"
  },
  "ci_status": {
    "pr_18_check": "pass",
    "pr_18_native_sdl_capture": "pass",
    "pr_18_installer_matrix": "pass"
  },
  "ci_fixes": [
    "lig_present_host_present_active -> lig_present_host_active",
    "ECOSYSTEM_REF + LIC_ROOT for native capture workflow",
    "verify scripts resolve lic package paths via LIC_ROOT",
    "sync ui-ux-by-dimension.md + profile-animate-memory.sh into studio",
    "chmod bench scripts; bench registry studio-local JSON fallback"
  ],
  "notes": "GUI library plan W0–W5 complete. All wsg-w* todos done. Local completion gate pass. PR #18 CI fully green after studio-repo consolidation fixes.",
  "pr_url": "https://github.com/li-langverse/studio/pull/18"
}
