{
  "pass": true,
  "todo_id": "wsg-w4-route-table",
  "agent_run": "world_studio_builder-61566124",
  "wps_touched": ["W4", "WP-UX-15", "PH-GD-1"],
  "smokes_run": [
    "packages/li-studio/li-tests/smoke/studio_route_table.li"
  ],
  "native_only": true,
  "route_table": {
    "route_count": 9,
    "keys": [
      "author/game",
      "simulate/scientific",
      "adaptive/drug/litl-0",
      "adaptive/drug/litl-1",
      "adaptive/drug/litl-2",
      "adaptive/drug/litl-3",
      "adaptive/drug/litl-4",
      "agent",
      "bench"
    ],
    "env": "STUDIO_ROUTE",
    "startup": "studio_route_resolve_startup"
  },
  "gates": {
    "world_studio_gui_plan_gates": "pass",
    "studio_route_table": "pass"
  },
  "notes": "StudioRoute table maps named shell configs to profile, mode, layout variant, LITL stage, and primary region; startup resolves STUDIO_ROUTE or STUDIO_DEMO_PROFILE/STUDIO_BENCH_MODE; vertical demo compose uses route table.",
  "pr_url": "https://github.com/li-langverse/studio/pull/18"
}
